{"name":"consumo del servicio delete exitoso","id":"consmo-de-servicios;consumo-del-servicio-delete-exitoso","testSteps":[{"number":1,"description":"When el  envia la peticion de eliminar el usuario \"2\"","duration":78,"startTime":"2022-03-27T23:36:06.610858-05:00[America/Bogota]","result":"PENDING","precondition":false,"level":0},{"number":2,"description":"Then el debera ver el codigo de respuesta","duration":25,"startTime":"2022-03-27T23:36:06.689429400-05:00[America/Bogota]","result":"IGNORED","precondition":false,"level":0}],"userStory":{"id":"consmo-de-servicios","storyName":"Consmo de servicios","displayName":"Consmo de servicios","path":"requestIn/consumo_servicios.feature","narrative":" Como usuario requiero realizar el consumo de los servios de registor y eliminacion","type":"feature"},"featureTag":{"name":"Request in/Consmo de servicios","type":"feature","displayName":"Request in/Consmo de servicios"},"title":"consumo del servicio delete exitoso","description":"","tags":[{"name":"Request in/Consmo de servicios","type":"feature","displayName":"Consmo de servicios"},{"name":"1","type":"tag","displayName":"1"},{"name":"Request in","type":"capability","displayName":"Request in"}],"startTime":"2022-03-27T23:36:05.982231100-05:00[America/Bogota]","duration":738,"projectKey":"","annotatedResult":"PENDING","isManualTestingUpToDate":false,"manual":false,"testSource":"Cucumber","result":"PENDING"}